README.md
setup.py
pulumi_nuage/__init__.py
pulumi_nuage/_utilities.py
pulumi_nuage/provider.py
pulumi_nuage/pulumi-plugin.json
pulumi_nuage/py.typed
pulumi_nuage.egg-info/PKG-INFO
pulumi_nuage.egg-info/SOURCES.txt
pulumi_nuage.egg-info/dependency_links.txt
pulumi_nuage.egg-info/not-zip-safe
pulumi_nuage.egg-info/requires.txt
pulumi_nuage.egg-info/top_level.txt
pulumi_nuage/aws/__init__.py
pulumi_nuage/aws/_enums.py
pulumi_nuage/aws/_inputs.py
pulumi_nuage/aws/bastion.py
pulumi_nuage/aws/container_function.py
pulumi_nuage/aws/image.py
pulumi_nuage/aws/repository.py
pulumi_nuage/aws/serverless_database.py