Metadata-Version: 2.1
Name: pulumi-nuage
Version: 0.1.0
Summary: UNKNOWN
Home-page: UNKNOWN
License: Apache-2.0
Keywords: pulumi aws nuage kind/component category/cloud
Platform: UNKNOWN
